{
  "Multiplayer": [
    {
      "image": "images/3DO Interactive MultIplayer/3DO-DMB-800-Console-transparent.png",
      "type": "Multiplayer",
      "name": "DMB-800-Console",
      "rate": "4.1",
      "price": "199.99"
    },
    {
      "image": "images/3DO Interactive MultIplayer/3DO-FZ1-Consoletransparent.png",
      "type": "Multiplayer",
      "name": "FZ-1-Console",
      "rate": "4.0",
      "price": "99.99"
    },
    {
      "image": "images/3DO Interactive MultIplayer/3DO-GDO-101M-Console-transparent.png",
      "type": "Multiplayer",
      "name": "GDO-101M-Console",
      "rate": "4.2",
      "price": "299.99"
    },
    {
      "image": "images/3DO Interactive MultIplayer/3DO-N1005-Console-transparent.png",
      "type": "Multiplayer",
      "name": "N1005-Console",
      "rate": "4.3",
      "price": "399.99"
    },
    {
      "image": "images/3DO Interactive MultIplayer/3DO-FZ-10-Console-transparent.png",
      "type": "Multiplayer",
      "name": "RY-Console-FL",
      "rate": "4.7",
      "price": "499.99"
    },
    {
      "image": "images/3DO Interactive MultIplayer/3DO-DMB-800-Console-transparent.png",
      "type": "Multiplayer",
      "name": "FZ-10-Console",
      "rate": "4.9",
      "price": "599.99"
    }
  ],
  "Game": [
    {
      "image": "images/3DO Game/Army_Men_3D.png",
      "type": "Game",
      "name": "Army Men 3D",
      "rate": "3.1",
      "price": "1.99"
    },
    {
      "image": "images/3DO Game/Army_Men-_Toys_in_Space.jpg",
      "type": "Game",
      "name": "Army Men:Toys in Space",
      "rate": "4.1",
      "price": "0.99"
    },
    {
      "image": "images/3DO Game/3DO_Games_Decathlon.webp",
      "type": "Game",
      "name": "3DO Games Decathlon",
      "rate": "3.9",
      "price": "2.99"
    },
    {
      "image": "images/3DO Game/Army_Men.png",
      "type": "Game",
      "name": "Army Men",
      "rate": "4.1",
      "price": "3.99"
    },
    {
      "image": "images/3DO Game/Army_Men_Air_Attack_2.jpg",
      "type": "Game",
      "name": "Army Men: Air Attack 2",
      "rate": "4.2",
      "price": "4.99"
    },
    {
      "image": "images/3DO Game/Army_Men_Air_Tactics.png",
      "type": "Game",
      "name": "Army Men:Air Tactics",
      "rate": "4.9",
      "price": "5.99"
    },
    {
      "image": "images/3DO Game/Army_Men_Green_Rogue.png",
      "type": "Game",
      "name": "Army Men: Green Rogue",
      "rate": "4.7",
      "price": "6.99"
    },
    {
      "image": "images/3DO Game/Army_Men_II_Coverart.png",
      "type": "Game",
      "name": "Army Men II",
      "rate": "4.3",
      "price": "7.99"
    },
    {
      "image": "images/3DO Game/Army_Men_Lock_N_Load.png",
      "type": "Game",
      "name": "Army Men: Lock N Load",
      "rate": "4.1",
      "price": "8.99"
    },
    {
      "image": "images/3DO Game/Army_Men_Sarge's_Heroes2.jpg",
      "type": "Game",
      "name": "Army Men: Sarge's Heroes 2",
      "rate": "4.5",
      "price": "9.99"
    },
    {
      "image": "images/3DO Game/Army_Men_Sarge’s_Heroes.jpg",
      "type": "Game",
      "name": "Army Men: Sarge's Heroes",
      "rate": "4.2",
      "price": "10.99"
    },
    {
      "image": "images/3DO Game/Army_Men_World_War.png",
      "type": "Game",
      "name": "Army Men: World War",
      "rate": "4.8",
      "price": "11.99"
    },
    {
      "image": "images/3DO Game/Army_Men_World_War_Land_Sea_Air.png",
      "type": "Game",
      "name": "Army Men: World War Land Sea Air",
      "rate": "4.6",
      "price": "12.99"
    },
    {
      "image": "images/3DO Game/Army_Men_World_War_Team_Assault.jpg",
      "type": "Game",
      "name": "Army Men: World War Team Assault",
      "rate": "4.9",
      "price": "13.99"
    },
    {
      "image": "images/3DO Game/BattleTanx.jpg",
      "type": "Game",
      "name": "BattleTanx",
      "rate": "4.0",
      "price": "14.99"
    },
    {
      "image": "images/3DO Game/BattleTanx_-_Global_Assault.jpg",
      "type": "Game",
      "name": "BattleTanx: Global Assault",
      "rate": "3.0",
      "price": "15.99"
    },
    {
      "image": "images/3DO Game/Capt Quazar.jpg",
      "type": "Game",
      "name": "Capt Quazar",
      "rate": "3.5",
      "price": "16.99"
    },
    {
      "image": "images/3DO Game/Crusaders O fMight And Magic Box.jpg",
      "type": "Game",
      "name": "Crusaders Of Might And Magic",
      "rate": "3.6",
      "price": "17.99"
    },
    {
      "image": "images/3DO Game/Dragon Rage Cover.jpeg",
      "type": "Game",
      "name": "Dragon Rage",
      "rate": "3.7",
      "price": "18.99"
    },
    {
      "image": "images/3DO Game/Godai Elemental Force.jpg",
      "type": "Game",
      "name": "Godai Elemental Force",
      "rate": "4.7",
      "price": "19.99"
    },
    {
      "image": "images/3DO Game/Gulf War Operation Desert Hammer.jpg",
      "type": "Game",
      "name": "Gulf War Operation Desert Hammer",
      "rate": "4.8",
      "price": "20.99"
    },
    {
      "image": "images/3DO Game/Heroes of Might and Magic II The Succession Wars.jpg",
      "type": "Game",
      "name": "Heroes of Might and Magic II: The Succession Wars",
      "rate": "4.0",
      "price": "21.99"
    },
    {
      "image": "images/3DO Game/Heroes of Might and Magic Quest for the Dragon Bone Staff.png",
      "type": "Game",
      "name": "Heroes of Might and Magic: Quest for the Dragon Bone Staff",
      "rate": "4.3",
      "price": "22.99"
    },
    {
      "image": "images/3DO Game/Heroes of Might and Magic.png",
      "type": "Game",
      "name": "Heroes of Might and Magic",
      "rate": "4.3",
      "price": "23.99"
    }
  ]
}
